<?xml version="1.0"?>
<!DOCTYPE hibernate-mapping PUBLIC "-//Hibernate/Hibernate Mapping DTD 3.0//EN"
"http://www.hibernate.org/dtd/hibernate-mapping-3.0.dtd">
<!-- Generated 12.05.2016 22:04:39 by Hibernate Tools 4.3.1 -->
<hibernate-mapping>
    <class name="mysqlBeans.Adresse" table="adresse" catalog="iib2_ue1_2_gruppe1" optimistic-lock="version">
        <id name="adrId" type="java.lang.Integer">
            <column name="adr_id" />
            <generator class="identity" />
        </id>
        <property name="adrStrasse" type="string">
            <column name="adr_strasse" length="45" />
        </property>
        <property name="adrHausnummer" type="string">
            <column name="adr_hausnummer" length="45" />
        </property>
        <property name="adrPlz" type="string">
            <column name="adr_plz" length="8" />
        </property>
        <property name="adrOrt" type="string">
            <column name="adr_ort" length="45" />
        </property>
        <property name="adrLand" type="string">
            <column name="adr_land" length="45" />
        </property>
        <set name="handwerkers" table="handwerker" inverse="true" lazy="true" fetch="select">
            <key>
                <column name="haw_adr_id" not-null="true" />
            </key>
            <one-to-many class="mysqlBeans.Handwerker" />
        </set>
        <set name="eigentuemers" table="eigentuemer" inverse="true" lazy="true" fetch="select">
            <key>
                <column name="eig_adr_id" not-null="true" />
            </key>
            <one-to-many class="mysqlBeans.Eigentuemer" />
        </set>
        <set name="gebaeudes" table="gebaeude" inverse="true" lazy="true" fetch="select">
            <key>
                <column name="gbd_adr_id" not-null="true" />
            </key>
            <one-to-many class="mysqlBeans.Gebaeude" />
        </set>
        <set name="gutachters" table="gutachter" inverse="true" lazy="true" fetch="select">
            <key>
                <column name="gut_adr_id" not-null="true" />
            </key>
            <one-to-many class="mysqlBeans.Gutachter" />
        </set>
    </class>
</hibernate-mapping>
